.gitignore
.travis.yml
CHANGES.txt
COPYRIGHT.txt
LICENSE.txt
MANIFEST.in
README.txt
bootstrap.py
buildout.cfg
repoze.session-1.0a1.tar.gz
setup.py
tox.ini
ztk-versions-1.1.2.cfg
src/cipher/__init__.py
src/cipher.session.egg-info/PKG-INFO
src/cipher.session.egg-info/SOURCES.txt
src/cipher.session.egg-info/dependency_links.txt
src/cipher.session.egg-info/not-zip-safe
src/cipher.session.egg-info/requires.txt
src/cipher.session.egg-info/top_level.txt
src/cipher/session/__init__.py
src/cipher/session/_compat.py
src/cipher/session/bootstrap.py
src/cipher/session/bootstrap.zcml
src/cipher/session/configure.zcml
src/cipher/session/credentials.py
src/cipher/session/interfaces.py
src/cipher/session/session.py
src/cipher/session/session.zcml
src/cipher/session/tests/__init__.py
src/cipher/session/tests/test_appendict.py
src/cipher/session/tests/test_data.py
src/cipher/session/tests/test_session.py